acryl_datahub_cloud/__init__.py
acryl_datahub_cloud/_codegen_config.json
acryl_datahub_cloud/graphql_utils.py
acryl_datahub_cloud/py.typed
acryl_datahub_cloud/acryl_cs_issues/__init__.py
acryl_datahub_cloud/acryl_cs_issues/acryl_customer.py
acryl_datahub_cloud/acryl_cs_issues/acryl_linear.py
acryl_datahub_cloud/acryl_cs_issues/acryl_slack.py
acryl_datahub_cloud/acryl_cs_issues/acryl_zendesk.py
acryl_datahub_cloud/acryl_cs_issues/models.py
acryl_datahub_cloud/acryl_cs_issues/source.py
acryl_datahub_cloud/action_request/__init__.py
acryl_datahub_cloud/action_request/action_request_owner_source.py
acryl_datahub_cloud/api/__init__.py
acryl_datahub_cloud/api/client.py
acryl_datahub_cloud/datahub_forms_notifications/__init__.py
acryl_datahub_cloud/datahub_forms_notifications/forms_notifications_source.py
acryl_datahub_cloud/datahub_forms_notifications/get_feature_flag.gql
acryl_datahub_cloud/datahub_forms_notifications/get_search_results_total.gql
acryl_datahub_cloud/datahub_forms_notifications/query.py
acryl_datahub_cloud/datahub_forms_notifications/scroll_forms_for_notification.gql
acryl_datahub_cloud/datahub_forms_notifications/send_form_notification_request.gql
acryl_datahub_cloud/datahub_metadata_sharing/__init__.py
acryl_datahub_cloud/datahub_metadata_sharing/metadata_sharing_source.py
acryl_datahub_cloud/datahub_metadata_sharing/query.py
acryl_datahub_cloud/datahub_metadata_sharing/scroll_shared_entities.gql
acryl_datahub_cloud/datahub_metadata_sharing/share_entity.gql
acryl_datahub_cloud/datahub_reporting/__init__.py
acryl_datahub_cloud/datahub_reporting/datahub_dataset.py
acryl_datahub_cloud/datahub_reporting/datahub_form_reporting.py
acryl_datahub_cloud/datahub_reporting/extract_graph.py
acryl_datahub_cloud/datahub_reporting/extract_sql.py
acryl_datahub_cloud/datahub_reporting/forms.py
acryl_datahub_cloud/datahub_reporting/forms_config.py
acryl_datahub_cloud/datahub_restore/__init__.py
acryl_datahub_cloud/datahub_restore/do_restore.py
acryl_datahub_cloud-0.3.16.dist-info/METADATA
acryl_datahub_cloud-0.3.16.dist-info/WHEEL
acryl_datahub_cloud-0.3.16.dist-info/entry_points.txt
acryl_datahub_cloud-0.3.16.dist-info/top_level.txt
acryl_datahub_cloud-0.3.16.dist-info/RECORD
